SlimMem/__init__.py
slimmem-0.0.1.dist-info/METADATA
slimmem-0.0.1.dist-info/WHEEL
slimmem-0.0.1.dist-info/top_level.txt
slimmem-0.0.1.dist-info/RECORD
