Metadata-Version: 2.4
Name: slimmem
Version: 0.0.1
Summary: Slim Memory.
Requires-Python: >=3.8
